log2http/__init__.py
log2http/app.py
log2http/const.py
log2http-0.1.1.dist-info/METADATA
log2http-0.1.1.dist-info/RECORD
log2http-0.1.1.dist-info/WHEEL
log2http-0.1.1.dist-info/entry_points.txt
log2http-0.1.1.dist-info/top_level.txt
