Metadata-Version: 2.1
Name: log2http
Version: 0.1.1
Summary: log2http watches log files and sends new contents to a specified http endpoint.
Home-page: https://github.com/davidhamann/log2http
Author: David Hamann
Author-email: dh@davidhamann.de
License: UNKNOWN
Platform: UNKNOWN
Classifier: Development Status :: 4 - Beta
Classifier: Programming Language :: Python
Classifier: Programming Language :: Python :: 3.6
Classifier: License :: OSI Approved :: MIT License
Classifier: Intended Audience :: System Administrators
Classifier: Operating System :: Unix
Classifier: Environment :: Console
Requires-Python: >=3.6
Requires-Dist: requests (>=2)
Requires-Dist: docopt (>=0.6.2)
Requires-Dist: mypy-extensions (>=0.4.1)
Requires-Dist: PyYAML (>=3.13)
